{
    "display": {
        "title": {
            "text": "Curious Sentient Waterborn"
        },
        "description": {
            "text": "Become a Morphling\nWater creature that seeks nothing but evolution"
        },
        "icon": {
            "item": "minecraft:light_blue_dye"
        },
        "frame": "task",
        "show_toast": true,
        "announce_to_chat": false,
        "hidden": false
    },
    "parent": "cyra:root",
    "criteria": {
        "1_water": {
            "trigger": "origins:chose_origin",
            "conditions": {
                "origin": "cyra:morphling/1_water"
            }
        }
    }
}